jpj/__init__.py
jpj/jpj.py
jpj/jpj_bag.py
jpj/jpj_signals.py
jpj-0.1.2.dist-info/LICENSE
jpj-0.1.2.dist-info/METADATA
jpj-0.1.2.dist-info/WHEEL
jpj-0.1.2.dist-info/entry_points.txt
jpj-0.1.2.dist-info/top_level.txt
jpj-0.1.2.dist-info/RECORD
