Metadata-Version: 2.1
Name: jpj
Version: 0.1.2
Summary: Draw Led Zeppelin's John Paul Jones' symbol
Author-email: Vincenzo Petrone <vipetrone@unisa.it>
License: MIT
Requires-Python: >=3.7
License-File: LICENSE
Requires-Dist: numpy
Requires-Dist: matplotlib
Requires-Dist: sympy
Requires-Dist: scipy
